aldryn_faq/__init__.py
aldryn_faq/admin.py
aldryn_faq/cms_appconfig.py
aldryn_faq/cms_apps.py
aldryn_faq/cms_menus.py
aldryn_faq/cms_plugins.py
aldryn_faq/cms_toolbars.py
aldryn_faq/cms_wizards.py
aldryn_faq/forms.py
aldryn_faq/managers.py
aldryn_faq/models.py
aldryn_faq/search_indexes.py
aldryn_faq/urls.py
aldryn_faq/utils.py
aldryn_faq/views.py
aldryn_faq/boilerplates/bootstrap3/templates/aldryn_faq/base.html
aldryn_faq/boilerplates/bootstrap3/templates/aldryn_faq/fullwidth.html
aldryn_faq/boilerplates/bootstrap3/templates/aldryn_faq/landing.html
aldryn_faq/boilerplates/bootstrap3/templates/aldryn_faq/question_detail.html
aldryn_faq/boilerplates/bootstrap3/templates/aldryn_faq/question_list.html
aldryn_faq/boilerplates/bootstrap3/templates/aldryn_faq/two_column.html
aldryn_faq/boilerplates/bootstrap3/templates/aldryn_faq/includes/pager.html
aldryn_faq/boilerplates/bootstrap3/templates/aldryn_faq/includes/question_list.html
aldryn_faq/boilerplates/bootstrap3/templates/aldryn_faq/includes/ungrouped_question_list.html
aldryn_faq/boilerplates/bootstrap3/templates/aldryn_faq/plugins/category_list.html
aldryn_faq/boilerplates/bootstrap3/templates/aldryn_faq/plugins/latest_questions.html
aldryn_faq/boilerplates/bootstrap3/templates/aldryn_faq/plugins/most_read_questions.html
aldryn_faq/boilerplates/bootstrap3/templates/aldryn_faq/plugins/question_list.html
aldryn_faq/boilerplates/bootstrap3/templates/aldryn_faq/plugins/top_questions.html
aldryn_faq/boilerplates/legacy/templates/aldryn_faq/base.html
aldryn_faq/boilerplates/legacy/templates/aldryn_faq/landing.html
aldryn_faq/boilerplates/legacy/templates/aldryn_faq/question_detail.html
aldryn_faq/boilerplates/legacy/templates/aldryn_faq/question_list.html
aldryn_faq/boilerplates/legacy/templates/aldryn_faq/includes/question_groups.html
aldryn_faq/boilerplates/legacy/templates/aldryn_faq/includes/question_list.html
aldryn_faq-2.1.2.dist-info/DESCRIPTION.rst
aldryn_faq-2.1.2.dist-info/METADATA
aldryn_faq-2.1.2.dist-info/RECORD
aldryn_faq-2.1.2.dist-info/WHEEL
aldryn_faq-2.1.2.dist-info/metadata.json
aldryn_faq-2.1.2.dist-info/top_level.txt
