Metadata-Version: 2.0
Name: aldryn-faq
Version: 2.1.2
Summary: FAQ addon for django CMS
Home-page: https://github.com/aldryn/aldryn-faq
Author: Divio AG
Author-email: info@divio.ch
License: LICENSE.txt
Platform: OS Independent
Classifier: Development Status :: 5 - Production/Stable
Classifier: Environment :: Web Environment
Classifier: Framework :: Django
Classifier: Framework :: Django :: 1.8
Classifier: Framework :: Django :: 1.9
Classifier: Framework :: Django :: 1.10
Classifier: Framework :: Django :: 1.11
Classifier: Intended Audience :: Developers
Classifier: License :: OSI Approved :: BSD License
Classifier: Operating System :: OS Independent
Classifier: Programming Language :: Python
Classifier: Programming Language :: Python :: 2.7
Classifier: Programming Language :: Python :: 3.3
Classifier: Programming Language :: Python :: 3.4
Classifier: Programming Language :: Python :: 3.5
Classifier: Topic :: Internet :: WWW/HTTP :: Dynamic Content
Classifier: Topic :: Software Development
Classifier: Topic :: Software Development :: Libraries :: Application Frameworks
Requires-Dist: aldryn-apphooks-config (>=0.4.0)
Requires-Dist: aldryn-boilerplates (<0.8,>=0.7.4)
Requires-Dist: aldryn-search
Requires-Dist: aldryn-translation-tools (>=0.2.1)
Requires-Dist: django (>=1.8,<2.0)
Requires-Dist: django-admin-sortable
Requires-Dist: django-admin-sortable2 (>=0.5.2)
Requires-Dist: django-cms (>=3.4)
Requires-Dist: django-parler (>=1.8.1)
Requires-Dist: django-sortedm2m (>=1.4.0)
Requires-Dist: django-taggit
Requires-Dist: djangocms-text-ckeditor
